{
  "id": "2206705",
  "name": "demo-test",
  "font_family": "iconfont",
  "css_prefix_text": "icon",
  "description": "",
  "glyphs": [
    {
      "icon_id": "1090753",
      "name": "住宿",
      "font_class": "zhusu",
      "unicode": "e732",
      "unicode_decimal": 59186
    },
    {
      "icon_id": "8661089",
      "name": "打车",
      "font_class": "dache",
      "unicode": "e644",
      "unicode_decimal": 58948
    },
    {
      "icon_id": "12785312",
      "name": "旅游",
      "font_class": "lvyou",
      "unicode": "e645",
      "unicode_decimal": 58949
    },
    {
      "icon_id": "12829963",
      "name": "美食",
      "font_class": "fenzu",
      "unicode": "e605",
      "unicode_decimal": 58885
    },
    {
      "icon_id": "13312382",
      "name": "电影",
      "font_class": "dianying",
      "unicode": "e60e",
      "unicode_decimal": 58894
    },
    {
      "icon_id": "17427657",
      "name": "美景",
      "font_class": "meijing",
      "unicode": "e6e5",
      "unicode_decimal": 59109
    },
    {
      "icon_id": "17852780",
      "name": "秒 杀2",
      "font_class": "miaosha2",
      "unicode": "e69c",
      "unicode_decimal": 59036
    },
    {
      "icon_id": "2794092",
      "name": "hi",
      "font_class": "hi",
      "unicode": "e60b",
      "unicode_decimal": 58891
    },
    {
      "icon_id": "9481576",
      "name": "花瓣",
      "font_class": "huaban",
      "unicode": "e60c",
      "unicode_decimal": 58892
    },
    {
      "icon_id": "13695707",
      "name": "订单",
      "font_class": "icon-",
      "unicode": "e60d",
      "unicode_decimal": 58893
    },
    {
      "icon_id": "6736907",
      "name": "快递",
      "font_class": "kuaidi",
      "unicode": "e600",
      "unicode_decimal": 58880
    },
    {
      "icon_id": "9614486",
      "name": "快递",
      "font_class": "kuaidi1",
      "unicode": "e629",
      "unicode_decimal": 58921
    },
    {
      "icon_id": "16008903",
      "name": "购物车-23",
      "font_class": "qicheqianlian-",
      "unicode": "e60a",
      "unicode_decimal": 58890
    },
    {
      "icon_id": "3952155",
      "name": "定位",
      "font_class": "location",
      "unicode": "e607",
      "unicode_decimal": 58887
    },
    {
      "icon_id": "10172816",
      "name": "二维码",
      "font_class": "qrcode",
      "unicode": "e609",
      "unicode_decimal": 58889
    },
    {
      "icon_id": "474525",
      "name": "联系人/个人中心",
      "font_class": "geren",
      "unicode": "e602",
      "unicode_decimal": 58882
    },
    {
      "icon_id": "5374647",
      "name": "发现",
      "font_class": "faxian",
      "unicode": "e619",
      "unicode_decimal": 58905
    },
    {
      "icon_id": "9498993",
      "name": "首页-选中",
      "font_class": "index",
      "unicode": "e601",
      "unicode_decimal": 58881
    },
    {
      "icon_id": "10793930",
      "name": "动态",
      "font_class": "dongtai",
      "unicode": "e723",
      "unicode_decimal": 59171
    },
    {
      "icon_id": "12191742",
      "name": "消 息",
      "font_class": "xiaoxi",
      "unicode": "e603",
      "unicode_decimal": 58883
    },
    {
      "icon_id": "12462169",
      "name": "联系人",
      "font_class": "lianxiren-copy",
      "unicode": "e604",
      "unicode_decimal": 58884
    },
    {
      "icon_id": "15882058",
      "name": "QQ看点",
      "font_class": "QQkandian",
      "unicode": "e608",
      "unicode_decimal": 58888
    },
    {
      "icon_id": "17012360",
      "name": "订单",
      "font_class": "order",
      "unicode": "e606",
      "unicode_decimal": 58886
    },
    {
      "icon_id": "17663580",
      "name": "联系人_个人",
      "font_class": "geren1",
      "unicode": "e7fd",
      "unicode_decimal": 59389
    }
  ]
}
